include/nlopt.h
include/nlopt.hpp
lib/cmake/nlopt/NLoptConfig.cmake
lib/cmake/nlopt/NLoptConfigVersion.cmake
lib/cmake/nlopt/NLoptLibraryDepends-release.cmake
lib/cmake/nlopt/NLoptLibraryDepends.cmake
lib/nlopt.lib
lib/pkgconfig/nlopt.pc
pygbs/__init__.py
pygbs/analysis.cp311-win_amd64.pyd
pygbs/bsCurveEditor.py
pygbs/build.cp311-win_amd64.pyd
pygbs/core.cp311-win_amd64.pyd
pygbs/gbs/__init__.py
pygbs/interpolate.cp311-win_amd64.pyd
pygbs/plotlyplot.py
pygbs/tools.cp311-win_amd64.pyd
pygbs/transform.cp311-win_amd64.pyd
pygbs-0.4.2.dist-info/METADATA
pygbs-0.4.2.dist-info/WHEEL
pygbs-0.4.2.dist-info/licenses/LICENSE
pygbs-0.4.2.dist-info/RECORD
